fw_gear_hierarchy_curator/__init__.py
fw_gear_hierarchy_curator/main.py
fw_gear_hierarchy_curator/parser.py
fw_gear_hierarchy_curator/utils.py
fw_gear_hierarchy_curator-3.0.1.dist-info/METADATA
fw_gear_hierarchy_curator-3.0.1.dist-info/WHEEL
fw_gear_hierarchy_curator-3.0.1.dist-info/RECORD
