Metadata-Version: 2.4
Name: fw-gear-hierarchy-curator
Version: 3.0.1
Summary: Custom hierarchy curation gear
Author-email: Flywheel <support@flywheel.io>
License-Expression: MIT
Requires-Python: ~=3.12
Requires-Dist: flywheel-sdk>=21.1.0
Requires-Dist: fw-client<3,>=2.1.1
Requires-Dist: fw-curation>=1.0.1
Requires-Dist: fw-file>=4.2.0
Requires-Dist: fw-gear>=0.3.2
Requires-Dist: ipykernel>=7.1.0
Requires-Dist: nibabel<6,>=5.3.2
Requires-Dist: pandas<3,>=2.2.3
Requires-Dist: piexif<2,>=1.1.3
Requires-Dist: pillow<12,>=11.1.0
Requires-Dist: pypng<1,>=0
